fastpluggy_plugin/scheduled_query/__init__.py
fastpluggy_plugin/scheduled_query/config.py
fastpluggy_plugin/scheduled_query/metrics.py
fastpluggy_plugin/scheduled_query/models.py
fastpluggy_plugin/scheduled_query/plugin.py
fastpluggy_plugin/scheduled_query/tasks.py
fastpluggy_plugin/scheduled_query/routers/__init__.py
fastpluggy_plugin/scheduled_query/routers/api_router.py
fastpluggy_plugin/scheduled_query/routers/crud_router.py
fastpluggy_plugin/scheduled_query/routers/web_router.py
fastpluggy_plugin/scheduled_query/templates/dashboard.html.j2
fastpluggy_plugin/scheduled_query/templates/edit_form.html.j2
fastpluggy_plugin/scheduled_query/templates/widgets/scheduled_query_result.html.j2
fastpluggy_plugin/scheduled_query/widgets/__init__.py
fastpluggy_plugin/scheduled_query/widgets/scheduled_query_result_widget.py
fastpluggy_scheduled_query-0.1.50.dist-info/METADATA
fastpluggy_scheduled_query-0.1.50.dist-info/WHEEL
fastpluggy_scheduled_query-0.1.50.dist-info/entry_points.txt
fastpluggy_scheduled_query-0.1.50.dist-info/top_level.txt
fastpluggy_scheduled_query-0.1.50.dist-info/RECORD
