Metadata-Version: 2.4
Name: fastpluggy-scheduled-query
Version: 0.1.50
Summary: Scheduled Query plugin for Fastpluggy
Author: FastPluggy Team
Requires-Python: >=3.10
Requires-Dist: fastpluggy-ui-tools
Requires-Dist: fastpluggy-tasks-worker>=0.3.0
Requires-Dist: loguru
Requires-Dist: prometheus_client
